Workbook
Name Slicer_Region: #N/A

Sheet Raw_Data
A1: Order_ID | B1: Order_Date | C1: Region | D1: City | E1: Sales_Channel | F1: Customer_Type | G1: Product | H1: Category | I1: Quantity | J1: Unit_Price_INR | K1: Discount | L1: Payment_Method | M1: Salesperson | N1: Order_Status | O1: Gross_Sales_INR | P1: Discount_Amount_INR | Q1: Net_Sales_INR | R1: Delivery_Days
A2: ORD-10585 | B2: 45839 | C2: North | D2: Lucknow | E2: Retail Store | F2: Individual | G2: Smartphone | H2: Electronics | I2: 5 | J2: 26500 | K2: 0 | L2: Cash on Delivery | M2: Rohan Sharma | N2: Delivered | O2: 132500 | P2: 0 | Q2: 132500 | R2: 3
A3: ORD-10397 | B3: 45839 | C3: West | D3: Surat | E3: Retail Store | F3: Small Business | G3: Backpack | H3: Accessories | I3: 1 | J3: 2500 | K3: 0.03 | L3: Net Banking | M3: Aarav Mehta | N3: Delivered | O3: 2500 | P3: 75 | Q3: 2425 | R3: 2
A4: ORD-10292 | B4: 45839 | C4: West | D4: Surat | E4: Retail Store | F4: Small Business | G4: Laptop | H4: Electronics | I4: 3 | J4: 57740 | K4: 0.05 | L4: Net Banking | M4: Priya Nair | N4: Delivered | O4: 173220 | P4: 8661 | Q4: 164559 | R4: 1
A5: ORD-10085 | B5: 45840 | C5: South | D5: Chennai | E5: Online | F5: Individual | G5: Mouse | H5: Accessories | I5: 3 | J5: 990 | K5: 0 | L5: Net Banking | M5: Vikram Singh | N5: Cancelled | O5: 0 | P5: 0 | Q5: 0
A6: ORD-10198 | B6: 45840 | C6: South | D6: Hyderabad | E6: Retail Store | F6: Individual | G6: Printer | H6: Office Equipment | I6: 2 | J6: 13300 | K6: 0.15 | L6: Cash on Delivery | M6: Sneha Iyer | N6: Delivered | O6: 26600 | P6: 3990 | Q6: 22610 | R6: 3
A7: ORD-10526 | B7: 45840 | C7: North | D7: Noida | E7: Retail Store | F7: Enterprise | G7: Smartphone | H7: Electronics | I7: 1 | J7: 29800 | K7: 0.1 | L7: Debit Card | M7: Karan Patel | N7: Delivered | O7: 29800 | P7: 2980 | Q7: 26820 | R7: 3
A8: ORD-10121 | B8: 45840 | C8: North | D8: Delhi | E8: Retail Store | F8: Small Business | G8: External SSD | H8: Storage | I8: 1 | J8: 6710 | K8: 0 | L8: Net Banking | M8: Vikram Singh | N8: Delivered | O8: 6710 | P8: 0 | Q8: 6710 | R8: 2
A9: ORD-10109 | B9: 45842 | C9: West | D9: Mumbai | E9: Online | F9: Small Business | G9: Keyboard | H9: Accessories | I9: 3 | J9: 1790 | K9: 0.05 | L9: Net Banking | M9: Sneha Iyer | N9: Delivered | O9: 5370 | P9: 268.5 | Q9: 5101.5 | R9: 3
A10: ORD-10527 | B10: 45842 | C10: West | D10: Mumbai | E10: Online | F10: Small Business | G10: External SSD | H10: Storage | I10: 2 | J10: 6850 | K10: 0.05 | L10: UPI | M10: Rohan Sharma | N10: Delivered | O10: 13700 | P10: 685 | Q10: 13015 | R10: 3
A11: ORD-10083 | B11: 45842 | C11: North | D11: Delhi | E11: Retail Store | F11: Enterprise | G11: External SSD | H11: Storage | I11: 4 | J11: 6700 | K11: 0.03 | L11: UPI | M11: Ananya Rao | N11: Delivered | O11: 26800 | P11: 804 | Q11: 25996 | R11: 4
A12: ORD-10320 | B12: 45842 | C12: West | D12: Surat | E12: Online | F12: Individual | G12: Keyboard | H12: Accessories | I12: 1 | J12: 1740 | K12: 0 | L12: Credit Card | M12: Priya Nair | N12: Delivered | O12: 1740 | P12: 0 | Q12: 1740 | R12: 4
A13: ORD-10530 | B13: 45843 | C13: West | D13: Mumbai | E13: Corporate | F13: Individual | G13: Mouse | H13: Accessories | I13: 5 | J13: 950 | K13: 0.1 | L13: UPI | M13: Neha Kapoor | N13: Delivered | O13: 4750 | P13: 475 | Q13: 4275 | R13: 3
A14: ORD-10565 | B14: 45843 | C14: South | D14: Hyderabad | E14: Online | F14: Individual | G14: Office Chair | H14: Furniture | I14: 2 | J14: 11810 | K14: 0.08 | L14: Credit Card | M14: Neha Kapoor | N14: Delivered | O14: 23620 | P14: 1889.6 | Q14: 21730.4 | R14: 2
A15: ORD-10375 | B15: 45844 | C15: South | D15: Chennai | E15: Retail Store | F15: Individual | G15: Laptop | H15: Electronics | I15: 3 | J15: 64490 | K15: 0 | L15: Net Banking | M15: Aarav Mehta | N15: Delivered | O15: 193470 | P15: 0 | Q15: 193470 | R15: 1
A16: ORD-10381 | B16: 45844 | C16: West | D16: Surat | E16: Online | F16: Individual | G16: Laptop | H16: Electronics | I16: 1 | J16: 64500 | K16: 0.08 | L16: Net Banking | M16: Priya Nair | N16: Delivered | O16: 64500 | P16: 5160 | Q16: 59340 | R16: 5
A17: ORD-10330 | B17: 45844 | C17: West | D17: Pune | E17: Retail Store | F17: Individual | G17: External SSD | H17: Storage | I17: 4 | J17: 7640 | K17: 0.05 | L17: Credit Card | M17: Priya Nair | N17: Delivered | O17: 30560 | P17: 1528 | Q17: 29032 | R17: 2
... A43: ORD-10327 | B43: 45861 | C43: North | D43: Delhi | E43: Corporate | F43: Individual | G43: Keyboard | H43: Accessories | I43: 1 | J43: 1740 | K43: 0.08 | L43: Net Banking | M43: Sneha Iyer | N43: Delivered | O43: 1740 | P43: 139.2 | Q43: 1600.8 | R43: 3
A44: ORD-10144 | B44: 45861 | C44: South | D44: Kochi | E44: Corporate | F44: Individual | G44: Wireless Headphones | H44: Electronics | I44: 1 | J44: 3170 | K44: 0 | L44: UPI | M44: Priya Nair | N44: Cancelled | O44: 0 | P44: 0 | Q44: 0
A45: ORD-10385 | B45: 45861 | C45: West | D45: Pune | E45: Retail Store | F45: Individual | G45: Mouse | H45: Accessories | I45: 2 | J45: 880 | K45: 0.08 | L45: Credit Card | M45: Rohan Sharma | N45: Delivered | O45: 1760 | P45: 140.8 | Q45: 1619.2 | R45: 1
A46: ORD-10631 | B46: 45861 | C46: South | D46: Hyderabad | E46: Corporate | F46: Enterprise | G46: Monitor | H46: Electronics | I46: 1 | J46: 17400 | K46: 0.05 | L46: UPI | M46: Karan Patel | N46: Delivered | O46: 17400 | P46: 870 | Q46: 16530 | R46: 3
A47: ORD-10432 | B47: 45863 | C47: West | D47: Mumbai | E47: Online | F47: Individual | G47: Wireless Headphones | H47: Electronics | I47: 1 | J47: 3030 | K47: 0.03 | L47: Net Banking | M47: Aarav Mehta | N47: Delivered | O47: 3030 | P47: 90.9 | Q47: 2939.1 | R47: 5
A48: ORD-10536 | B48: 45863 | C48: South | D48: Kochi | E48: Corporate | F48: Small Business | G48: Wireless Headphones | H48: Electronics | I48: 2 | J48: 3140 | K48: 0.1 | L48: Debit Card | M48: Karan Patel | N48: Delivered | O48: 6280 | P48: 628 | Q48: 5652 | R48: 2
A49: ORD-10328 | B49: 45863 | C49: West | D49: Ahmedabad | E49: Corporate | F49: Individual | G49: Laptop | H49: Electronics | I49: 2 | J49: 60000 | K49: 0.03 | L49: UPI | M49: Sneha Iyer | N49: Delivered | O49: 120000 | P49: 3600 | Q49: 116400 | R49: 2
A50: ORD-10476 | B50: 45863 | C50: East | D50: Bhubaneswar | E50: Retail Store | F50: Enterprise | G50: Laptop | H50: Electronics | I50: 1 | J50: 59470 | K50: 0.08 | L50: Debit Card | M50: Karan Patel | N50: Delivered | O50: 59470 | P50: 4757.6 | Q50: 54712.4 | R50: 1
A51: ORD-10590 | B51: 45865 | C51: North | D51: Delhi | E51: Online | F51: Small Business | G51: Laptop | H51: Electronics | I51: 1 | J51: 65160 | K51: 0 | L51: Credit Card | M51: Ananya Rao | N51: Delivered | O51: 65160 | P51: 0 | Q51: 65160 | R51: 2
A52: ORD-10143 | B52: 45865 | C52: South | D52: Chennai | E52: Online | F52: Small Business | G52: Printer | H52: Office Equipment | I52: 1 | J52: 13060 | K52: 0.08 | L52: UPI | M52: Vikram Singh | N52: Delivered | O52: 13060 | P52: 1044.8 | Q52: 12015.2 | R52: 4
A53: ORD-10141 | B53: 45865 | C53: North | D53: Lucknow | E53: Online | F53: Individual | G53: Power Bank | H53: Accessories | I53: 2 | J53: 1680 | K53: 0.03 | L53: UPI | M53: Priya Nair | N53: Delivered | O53: 3360 | P53: 100.8 | Q53: 3259.2 | R53: 4
A54: ORD-10305 | B54: 45866 | C54: South | D54: Bengaluru | E54: Retail Store | F54: Individual | G54: Laptop | H54: Electronics | I54: 3 | J54: 65510 | K54: 0.08 | L54: Credit Card | M54: Neha Kapoor | N54: Delivered | O54: 196530 | P54: 15722.4 | Q54: 180807.6 | R54: 3
A55: ORD-10507 | B55: 45866 | C55: West | D55: Surat | E55: Online | F55: Small Business | G55: Wireless Headphones | H55: Electronics | I55: 5 | J55: 3320 | K55: 0.05 | L55: UPI | M55: Priya Nair | N55: Delivered | O55: 16600 | P55: 830 | Q55: 15770 | R55: 3
A56: ORD-10388 | B56: 45866 | C56: North | D56: Delhi | E56: Retail Store | F56: Enterprise | G56: Wireless Headphones | H56: Electronics | I56: 1 | J56: 3310 | K56: 0.05 | L56: Debit Card | M56: Neha Kapoor | N56: Delivered | O56: 3310 | P56: 165.5 | Q56: 3144.5 | R56: 4
... A74: ORD-10110 | B74: 45875 | C74: West | D74: Surat | E74: Online | F74: Individual | G74: Monitor | H74: Electronics | I74: 1 | J74: 15970 | K74: 0 | L74: Credit Card | M74: Priya Nair | N74: Delivered | O74: 15970 | P74: 0 | Q74: 15970 | R74: 6
A75: ORD-10332 | B75: 45875 | C75: North | E75: Corporate | F75: Small Business | G75: Webcam | H75: Accessories | I75: 1 | J75: 3670 | K75: 0 | L75: Debit Card | M75: Aarav Mehta | N75: Delivered | O75: 3670 | P75: 0 | Q75: 3670 | R75: 2
A76: ORD-10171 | B76: 45877 | C76: South | D76: Bengaluru | E76: Corporate | F76: Small Business | G76: Webcam | H76: Accessories | I76: 3 | J76: 3770 | K76: 0.03 | L76: UPI | M76: Karan Patel | N76: Delivered | O76: 11310 | P76: 339.3 | Q76: 10970.7 | R76: 2
A77: ORD-10030 | B77: 45877 | C77: North | D77: Delhi | E77: Corporate | F77: Individual | G77: Office Desk | H77: Furniture | I77: 5 | J77: 14360 | K77: 0.1 | L77: Debit Card | M77: Rohan Sharma | N77: Delivered | O77: 71800 | P77: 7180 | Q77: 64620 | R77: 5
A78: ORD-10264 | B78: 45877 | C78: North | D78: Lucknow | E78: Retail Store | F78: Individual | G78: Wireless Headphones | H78: Electronics | I78: 4 | J78: 3120 | K78: 0.05 | L78: Debit Card | M78: Neha Kapoor | N78: Delivered | O78: 12480 | P78: 624 | Q78: 11856 | R78: 3
A79: ORD-10020 | B79: 45879 | C79: East | D79: Bhubaneswar | E79: Online | F79: Individual | G79: Mouse | H79: Accessories | I79: 3 | J79: 960 | K79: 0.15 | L79: Cash on Delivery | M79: Sneha Iyer | N79: Delivered | O79: 2880 | P79: 432 | Q79: 2448 | R79: 6
A80: ORD-10352 | B80: 45879 | C80: South | D80: Bengaluru | E80: Online | F80: Individual | G80: Mouse | H80: Accessories | I80: 2 | J80: 920 | K80: 0.08 | L80: UPI | M80: Priya Nair | N80: Delivered | O80: 1840 | P80: 147.2 | Q80: 1692.8 | R80: 5
A81: ORD-10055 | B81: 45879 | C81: South | D81: Kochi | E81: Retail Store | F81: Individual | G81: Power Bank | H81: Accessories | I81: 1 | J81: 1900 | K81: 0.1 | L81: Net Banking | M81: Aarav Mehta | N81: Delivered | O81: 1900 | P81: 190 | Q81: 1710 | R81: 4
A82: ORD-10147 | B82: 45880 | C82: West | D82: Pune | E82: Online | F82: Individual | G82: Keyboard | H82: Accessories | I82: 1 | J82: 1900 | K82: 0.05 | L82: UPI | M82: Aarav Mehta | N82: Delivered | O82: 1900 | P82: 95 | Q82: 1805 | R82: 4
A83: ORD-10482 | B83: 45880 | C83: West | D83: Ahmedabad | E83: Corporate | F83: Individual | G83: Office Desk | H83: Furniture | I83: 1 | J83: 14010 | K83: 0 | L83: Credit Card | M83: Neha Kapoor | N83: Delivered | O83: 14010 | P83: 0 | Q83: 14010 | R83: 1
A84: ORD-10612 | B84: 45881 | C84: South | D84: Chennai | E84: Corporate | F84: Individual | G84: Webcam | H84: Accessories | I84: 1 | J84: 3390 | K84: 0.1 | L84: UPI | M84: Neha Kapoor | N84: Delivered | O84: 3390 | P84: 339 | Q84: 3051 | R84: 2
A85: ORD-10490 | B85: 45881 | C85: North | D85: Lucknow | E85: Online | F85: Individual | G85: Office Chair | H85: Furniture | I85: 1 | J85: 11610 | K85: 0 | L85: UPI | M85: Neha Kapoor | N85: Delivered | O85: 11610 | P85: 0 | Q85: 11610 | R85: 6
A86: ORD-10422 | B86: 45882 | C86: West | D86: Mumbai | E86: Online | F86: Small Business | G86: Laptop | H86: Electronics | I86: 4 | J86: 63800 | K86: 0.1 | L86: Cash on Delivery | M86: Rohan Sharma | N86: Delivered | O86: 255200 | P86: 25520 | Q86: 229680 | R86: 5
A87: ORD-10486 | B87: 45883 | C87: South | D87: Bengaluru | E87: Retail Store | F87: Enterprise | G87: Printer | H87: Office Equipment | I87: 1 | J87: 12800 | K87: 0.05 | L87: Debit Card | M87: Vikram Singh | N87: Delivered | O87: 12800 | P87: 640 | Q87: 12160 | R87: 1
... A120: ORD-10436 | B120: 45898 | C120: North | D120: Jaipur | E120: Retail Store | F120: Individual | G120: Office Chair | H120: Furniture | I120: 2 | J120: 10780 | K120: 0.08 | L120: Debit Card | M120: Neha Kapoor | N120: Delivered | O120: 21560 | P120: 1724.8 | Q120: 19835.2 | R120: 2
A121: ORD-10072 | B121: 45901 | C121: South | D121: Kochi | E121: Retail Store | F121: Small Business | G121: Webcam | H121: Accessories | I121: 1 | J121: 3750 | K121: 0.08 | L121: UPI | M121: Rohan Sharma | N121: Cancelled | O121: 0 | P121: 0 | Q121: 0
A122: ORD-10273 | B122: 45901 | C122: West | D122: Surat | E122: Retail Store | F122: Individual | G122: Mouse | H122: Accessories | I122: 1 | J122: 910 | K122: 0.15 | L122: Debit Card | M122: Ananya Rao | N122: Delivered | O122: 910 | P122: 136.5 | Q122: 773.5 | R122: 3
A123: ORD-10060 | B123: 45901 | C123: West | D123: Surat | E123: Corporate | F123: Individual | G123: Smartphone | H123: Electronics | I123: 4 | J123: 27810 | K123: 0.03 | L123: Credit Card | M123: Karan Patel | N123: Delivered | O123: 111240 | P123: 3337.2 | Q123: 107902.8 | R123: 5
A124: ORD-10369 | B124: 45903 | C124: South | D124: Bengaluru | E124: Online | F124: Individual | G124: External SSD | H124: Storage | I124: 1 | J124: 6750 | K124: 0 | L124: Net Banking | M124: Rohan Sharma | N124: Delivered | O124: 6750 | P124: 0 | Q124: 6750 | R124: 6
A125: ORD-10452 | B125: 45903 | C125: West | D125: Mumbai | E125: Online | F125: Individual | G125: Backpack | H125: Accessories | I125: 1 | J125: 2450 | K125: 0 | L125: UPI | M125: Ananya Rao | N125: Delivered | O125: 2450 | P125: 0 | Q125: 2450 | R125: 2
A126: ORD-10363 | B126: 45904 | C126: South | D126: Hyderabad | E126: Online | F126: Individual | G126: Monitor | H126: Electronics | I126: 5 | J126: 15940 | K126: 0.1 | L126: Net Banking | M126: Rohan Sharma | N126: Delivered | O126: 79700 | P126: 7970 | Q126: 71730 | R126: 2
A127: ORD-10033 | B127: 45904 | C127: West | D127: Pune | E127: Online | F127: Individual | G127: External SSD | H127: Storage | I127: 5 | J127: 7250 | K127: 0.08 | L127: Credit Card | M127: Rohan Sharma | N127: Delivered | O127: 36250 | P127: 2900 | Q127: 33350 | R127: 2
A128: ORD-10249 | B128: 45904 | C128: South | D128: Hyderabad | E128: Retail Store | F128: Small Business | G128: Tablet | H128: Electronics | I128: 2 | J128: 22660 | K128: 0.05 | L128: Credit Card | M128: Sneha Iyer | N128: Delivered | O128: 45320 | P128: 2266 | Q128: 43054 | R128: 4
A129: ORD-10315 | B129: 45906 | C129: South | D129: Bengaluru | E129: Retail Store | F129: Small Business | G129: Smartphone | H129: Electronics | I129: 4 | J129: 26590 | K129: 0.08 | L129: Debit Card | M129: Aarav Mehta | N129: Delivered | O129: 106360 | P129: 8508.8 | Q129: 97851.2 | R129: 7
A130: ORD-10300 | B130: 45907 | C130: South | D130: Hyderabad | E130: Online | F130: Small Business | G130: Mouse | H130: Accessories | I130: 2 | J130: 910 | K130: 0 | L130: Credit Card | M130: Neha Kapoor | N130: Delivered | O130: 1820 | P130: 0 | Q130: 1820 | R130: 3
A131: ORD-10608 | B131: 45907 | C131: South | D131: Kochi | E131: Retail Store | F131: Individual | G131: Mouse | H131: Accessories | I131: 3 | J131: 910 | K131: 0.05 | L131: Credit Card | M131: Ananya Rao | N131: Delivered | O131: 2730 | P131: 136.5 | Q131: 2593.5 | R131: 3
A132: ORD-10277 | B132: 45907 | C132: South | D132: Hyderabad | E132: Online | F132: Individual | G132: Tablet | H132: Electronics | I132: 1 | J132: 22380 | K132: 0 | L132: Credit Card | M132: Sneha Iyer | N132: Delivered | O132: 22380 | P132: 0 | Q132: 22380 | R132: 3
A133: ORD-10573 | B133: 45908 | C133: North | D133: Lucknow | E133: Online | F133: Enterprise | G133: Backpack | H133: Accessories | I133: 1 | J133: 2480 | K133: 0 | L133: Credit Card | M133: Sneha Iyer | N133: Delivered | O133: 2480 | P133: 0 | Q133: 2480 | R133: 2
A134: ORD-10395 | B134: 45908 | C134: West | D134: Mumbai | E134: Retail Store | F134: Individual | G134: Wireless Headphones | H134: Electronics | I134: 2 | J134: 3340 | K134: 0 | L134: Net Banking | N134: Delivered | O134: 6680 | P134: 0 | Q134: 6680 | R134: 4
A135: ORD-10435 | B135: 45908 | C135: West | D135: Surat | E135: Online | F135: Small Business | G135: Webcam | H135: Accessories | I135: 4 | J135: 3520 | K135: 0.05 | L135: Debit Card | M135: Priya Nair | N135: Delivered | O135: 14080 | P135: 704 | Q135: 13376 | R135: 3
A136: ORD-10282 | B136: 45908 | C136: South | D136: Hyderabad | E136: Corporate | F136: Individual | G136: Monitor | H136: Electronics | I136: 3 | J136: 17020 | K136: 0.05 | L136: UPI | M136: Neha Kapoor | N136: Delivered | O136: 51060 | P136: 2553 | Q136: 48507 | R136: 4
A137: ORD-10510 | B137: 45909 | C137: West | D137: Mumbai | E137: Online | F137: Small Business | G137: Office Desk | H137: Furniture | I137: 1 | J137: 14090 | K137: 0.05 | L137: UPI | M137: Karan Patel | N137: Delivered | O137: 14090 | P137: 704.5 | Q137: 13385.5 | R137: 1
A138: ORD-10137 | B138: 45909 | C138: North | D138: Jaipur | E138: Online | F138: Individual | G138: Office Chair | H138: Furniture | I138: 2 | J138: 11840 | K138: 0.1 | L138: Net Banking | M138: Neha Kapoor | N138: Delivered | O138: 23680 | P138: 2368 | Q138: 21312 | R138: 5
A139: ORD-10269 | B139: 45909 | C139: West | D139: Pune | E139: Online | F139: Small Business | G139: Laptop | H139: Electronics | I139: 1 | J139: 61250 | K139: 0.03 | L139: UPI | M139: Vikram Singh | N139: Delivered | O139: 61250 | P139: 1837.5 | Q139: 59412.5 | R139: 5
A140: ORD-10418 | B140: 45910 | C140: East | D140: Guwahati | E140: Online | F140: Individual | G140: Smartphone | H140: Electronics | I140: 3 | J140: 27950 | K140: 0.05 | L140: UPI | M140: Neha Kapoor | N140: Delivered | O140: 83850 | P140: 4192.5 | Q140: 79657.5 | R140: 4
A141: ORD-10148 | B141: 45911 | C141: North | D141: Delhi | E141: Online | F141: Individual | G141: Printer | H141: Office Equipment | I141: 1 | J141: 11840 | K141: 0.03 | L141: UPI | M141: Karan Patel | N141: Delivered | O141: 11840 | P141: 355.2 | Q141: 11484.8 | R141: 3
A142: ORD-10623 | B142: 45911 | C142: West | D142: Ahmedabad | E142: Corporate | F142: Individual | G142: Office Chair | H142: Furniture | I142: 3 | J142: 10760 | K142: 0.1 | L142: UPI | M142: Priya Nair | N142: Delivered | O142: 32280 | P142: 3228 | Q142: 29052 | R142: 3
A143: ORD-10101 | B143: 45912 | C143: East | D143: Bhubaneswar | E143: Retail Store | F143: Individual | G143: Office Desk | H143: Furniture | I143: 2 | J143: 14850 | K143: 0.08 | L143: Net Banking | M143: Priya Nair | N143: Delivered | O143: 29700 | P143: 2376 | Q143: 27324 | R143: 4
A144: ORD-10367 | B144: 45912 | C144: South | D144: Hyderabad | E144: Online | F144: Enterprise | G144: Mouse | H144: Accessories | I144: 1 | J144: 990 | K144: 0.08 | L144: UPI | M144: Neha Kapoor | N144: Delivered | O144: 990 | P144: 79.2 | Q144: 910.8 | R144: 7
A145: ORD-10428 | B145: 45913 | C145: West | D145: Mumbai | E145: Online | F145: Individual | G145: Laptop | H145: Electronics | I145: 1 | J145: 59920 | K145: 0.05 | L145: Cash on Delivery | M145: Rohan Sharma | N145: Delivered | O145: 59920 | P145: 2996 | Q145: 56924 | R145: 2
A146: ORD-10291 | B146: 45913 | C146: South | D146: Bengaluru | E146: Corporate | F146: Small Business | G146: Wireless Headphones | H146: Electronics | I146: 3 | J146: 3280 | K146: 0.05 | L146: Cash on Delivery | M146: Aarav Mehta | N146: Delivered | O146: 9840 | P146: 492 | Q146: 9348 | R146: 3
... A155: ORD-10177 | B155: 45919 | C155: North | D155: Lucknow | E155: Online | F155: Individual | G155: External SSD | H155: Storage | I155: 4 | J155: 7220 | K155: 0 | L155: Net Banking | M155: Rohan Sharma | N155: Delivered | O155: 28880 | P155: 0 | Q155: 28880 | R155: 3
A156: ORD-10224 | B156: 45919 | C156: North | D156: Noida | E156: Retail Store | F156: Small Business | G156: Mouse | H156: Accessories | I156: 1 | J156: 940 | K156: 0.03 | L156: UPI | M156: Rohan Sharma | N156: Cancelled | O156: 0 | P156: 0 | Q156: 0
A157: ORD-10152 | B157: 45921 | C157: South | D157: Chennai | E157: Online | F157: Individual | G157: Office Chair | H157: Furniture | I157: 2 | J157: 11640 | K157: 0.08 | L157: UPI | M157: Ananya Rao | N157: Delivered | O157: 23280 | P157: 1862.4 | Q157: 21417.6 | R157: 5
A158: ORD-10131 | B158: 45922 | C158: South | D158: Hyderabad | E158: Retail Store | F158: Enterprise | G158: Office Chair | H158: Furniture | I158: 1 | J158: 10900 | K158: 0 | L158: UPI | M158: Vikram Singh | N158: Delivered | O158: 10900 | P158: 0 | Q158: 10900 | R158: 2
A159: ORD-10419 | B159: 45923 | C159: East | D159: Bhubaneswar | E159: Online | F159: Individual | G159: Keyboard | H159: Accessories | I159: 3 | J159: 1750 | K159: 0 | L159: Cash on Delivery | M159: Ananya Rao | N159: Returned | O159: 5250 | P159: 0 | Q159: 5250 | R159: 3
A160: ORD-10057 | B160: 45923 | C160: East | D160: Guwahati | E160: Online | F160: Small Business | G160: Office Desk | H160: Furniture | I160: 2 | J160: 15160 | K160: 0.05 | L160: UPI | M160: Ananya Rao | N160: Delivered | O160: 30320 | P160: 1516 | Q160: 28804 | R160: 4
A161: ORD-10031 | B161: 45924 | C161: North | D161: Lucknow | E161: Corporate | F161: Individual | G161: Laptop | H161: Electronics | I161: 1 | J161: 57830 | K161: 0.08 | L161: UPI | M161: Ananya Rao | N161: Delivered | O161: 57830 | P161: 4626.4 | Q161: 53203.6 | R161: 3
A162: ORD-10256 | B162: 45926 | C162: South | D162: Bengaluru | E162: Online | F162: Small Business | G162: External SSD | H162: Storage | I162: 2 | J162: 6830 | K162: 0.05 | L162: UPI | M162: Neha Kapoor | N162: Delivered | O162: 13660 | P162: 683 | Q162: 12977 | R162: 2
A163: ORD-10080 | B163: 45927 | C163: North | D163: Jaipur | E163: Retail Store | F163: Enterprise | G163: Tablet | H163: Electronics | I163: 3 | J163: 21800 | K163: 0.05 | L163: UPI | M163: Priya Nair | N163: Delivered | O163: 65400 | P163: 3270 | Q163: 62130 | R163: 2
A164: ORD-10310 | B164: 45927 | C164: South | D164: Hyderabad | E164: Retail Store | F164: Individual | G164: Mouse | H164: Accessories | I164: 1 | J164: 990 | K164: 0.03 | L164: UPI | M164: Vikram Singh | N164: Delivered | O164: 990 | P164: 29.7 | Q164: 960.3 | R164: 2
A165: ORD-10368 | B165: 45927 | C165: West | D165: Ahmedabad | E165: Corporate | F165: Individual | G165: Wireless Headphones | H165: Electronics | I165: 1 | J165: 3280 | K165: 0.08 | L165: Net Banking | M165: Karan Patel | N165: Cancelled | O165: 0 | P165: 0 | Q165: 0
A166: ORD-10458 | B166: 45927 | C166: West | D166: Pune | E166: Retail Store | F166: Individual | G166: Webcam | H166: Accessories | I166: 3 | J166: 3580 | K166: 0.08 | L166: Credit Card | M166: Aarav Mehta | N166: Delivered | O166: 10740 | P166: 859.2 | Q166: 9880.8 | R166: 4
A167: ORD-10535 | B167: 45928 | C167: West | D167: Mumbai | E167: Online | F167: Individual | G167: Smartphone | H167: Electronics | I167: 3 | J167: 29910 | K167: 0.05 | L167: UPI | M167: Aarav Mehta | N167: Delivered | O167: 89730 | P167: 4486.5 | Q167: 85243.5 | R167: 4
A168: ORD-10262 | B168: 45928 | C168: East | D168: Guwahati | E168: Online | F168: Small Business | G168: External SSD | H168: Storage | I168: 1 | J168: 7040 | K168: 0.03 | L168: Credit Card | M168: Karan Patel | N168: Delivered | O168: 7040 | P168: 211.2 | Q168: 6828.8 | R168: 2
A169: ORD-10183 | B169: 45928 | C169: South | D169: Hyderabad | E169: Retail Store | F169: Individual | G169: Office Chair | H169: Furniture | I169: 1 | J169: 11810 | K169: 0 | L169: Credit Card | M169: Karan Patel | N169: Delivered | O169: 11810 | P169: 0 | Q169: 11810 | R169: 7
A170: ORD-10022 | B170: 45928 | C170: South | D170: Kochi | E170: Retail Store | F170: Individual | G170: Mouse | H170: Accessories | I170: 2 | J170: 1000 | K170: 0 | L170: Debit Card | M170: Ananya Rao | N170: Delivered | O170: 2000 | P170: 0 | Q170: 2000 | R170: 5
A171: ORD-10619 | B171: 45929 | C171: South | D171: Kochi | E171: Online | F171: Enterprise | G171: Smartphone | H171: Electronics | I171: 2 | J171: 27300 | K171: 0.08 | L171: Net Banking | M171: Vikram Singh | N171: Delivered | O171: 54600 | P171: 4368 | Q171: 50232 | R171: 3
A172: ORD-10230 | B172: 45930 | C172: West | D172: Pune | E172: Corporate | F172: Individual | G172: Smartphone | H172: Electronics | I172: 1 | J172: 27340 | K172: 0.05 | L172: Debit Card | M172: Karan Patel | N172: Delivered | O172: 27340 | P172: 1367 | Q172: 25973 | R172: 2
A173: ORD-10104 | B173: 45930 | C173: West | D173: Pune | E173: Retail Store | F173: Individual | G173: Webcam | H173: Accessories | I173: 1 | J173: 3400 | K173: 0.05 | L173: Debit Card | M173: Karan Patel | N173: Delivered | O173: 3400 | P173: 170 | Q173: 3230 | R173: 3
A174: ORD-10160 | B174: 45931 | C174: South | D174: Hyderabad | E174: Retail Store | F174: Enterprise | G174: Backpack | H174: Accessories | I174: 3 | J174: 2510 | K174: 0.05 | L174: Net Banking | M174: Aarav Mehta | N174: Cancelled | O174: 0 | P174: 0 | Q174: 0
A175: ORD-10189 | B175: 45932 | C175: East | D175: Kolkata | E175: Corporate | F175: Small Business | G175: External SSD | H175: Storage | I175: 4 | J175: 6720 | K175: 0.15 | L175: Credit Card | M175: Rohan Sharma | N175: Delivered | O175: 26880 | P175: 4032 | Q175: 22848 | R175: 3
A176: ORD-10297 | B176: 45933 | C176: South | D176: Chennai | E176: Corporate | F176: Small Business | G176: Webcam | H176: Accessories | I176: 1 | J176: 3410 | K176: 0.05 | L176: UPI | M176: Aarav Mehta | N176: Delivered | O176: 3410 | P176: 170.5 | Q176: 3239.5 | R176: 5
A177: ORD-10361 | B177: 45934 | C177: South | D177: Bengaluru | E177: Retail Store | F177: Small Business | G177: Power Bank | H177: Accessories | I177: 3 | J177: 1700 | K177: 0 | L177: Net Banking | M177: Neha Kapoor | N177: Delivered | O177: 5100 | P177: 0 | Q177: 5100 | R177: 2
A178: ORD-10246 | B178: 45935 | C178: South | D178: Chennai | E178: Retail Store | F178: Individual | G178: Laptop | H178: Electronics | I178: 2 | J178: 66280 | K178: 0.03 | L178: Net Banking | M178: Sneha Iyer | N178: Delivered | O178: 132560 | P178: 3976.8 | Q178: 128583.2 | R178: 4
A179: ORD-10382 | B179: 45935 | C179: East | D179: Kolkata | E179: Retail Store | F179: Individual | G179: Tablet | H179: Electronics | I179: 1 | J179: 23320 | K179: 0.05 | L179: Cash on Delivery | M179: Rohan Sharma | N179: Delivered | O179: 23320 | P179: 1166 | Q179: 22154 | R179: 5
A180: ORD-10235 | B180: 45936 | C180: West | D180: Surat | E180: Retail Store | F180: Individual | G180: Laptop | H180: Electronics | I180: 1 | J180: 57700 | K180: 0.03 | L180: Cash on Delivery | M180: Neha Kapoor | N180: Delivered | O180: 57700 | P180: 1731 | Q180: 55969 | R180: 4
A181: ORD-10065 | B181: 45937 | C181: East | D181: Guwahati | E181: Online | F181: Small Business | G181: Mouse | H181: Accessories | I181: 1 | J181: 1010 | K181: 0.08 | L181: Debit Card | M181: Rohan Sharma | N181: Delivered | O181: 1010 | P181: 80.8 | Q181: 929.2 | R181: 4
A182: ORD-10600 | B182: 45937 | C182: East | D182: Bhubaneswar | E182: Online | F182: Individual | G182: Office Desk | H182: Furniture | I182: 2 | J182: 14130 | K182: 0.15 | L182: Net Banking | M182: Priya Nair | N182: Delivered | O182: 28260 | P182: 4239 | Q182: 24021 | R182: 2
...

Sheet Cleaned_data
A1: Order ID | B1: Order Date | C1: Region | D1: City | E1: Sales Channel | F1: Customer Type | G1: Product | H1: Category | I1: Quantity | J1: Unit Price INR | K1: Discount | L1: Payment Method | M1: Salesperson | N1: Order Status | O1: Gross Sales INR | P1: Discount Amount INR | Q1: Net Sales INR | R1: Delivery Days | S1: Sales Month
A2: ORD-10585 | B2: 45839 | C2: North | D2: Lucknow | E2: Retail Store | F2: Individual | G2: Smartphone | H2: Electronics | I2: 5 | J2: 26500 | K2: 0 | L2: Cash on Delivery | M2: Rohan Sharma | N2: Delivered | O2: 132500 | P2: 0 | Q2: 132500 | R2: 3 | S2: =DATE(YEAR(B2),MONTH(B2),1) -> 45839
A3: ORD-10397 | B3: 45839 | C3: West | D3: Surat | E3: Retail Store | F3: Small Business | G3: Backpack | H3: Accessories | I3: 1 | J3: 2500 | K3: 0.03 | L3: Net Banking | M3: Aarav Mehta | N3: Delivered | O3: 2500 | P3: 75 | Q3: 2425 | R3: 2 | S3: =DATE(YEAR(B3),MONTH(B3),1) -> 45839
A4: ORD-10292 | B4: 45839 | C4: West | D4: Surat | E4: Retail Store | F4: Small Business | G4: Laptop | H4: Electronics | I4: 3 | J4: 57740 | K4: 0.05 | L4: Net Banking | M4: Priya Nair | N4: Delivered | O4: 173220 | P4: 8661 | Q4: 164559 | R4: 1 | S4: =DATE(YEAR(B4),MONTH(B4),1) -> 45839
A5: ORD-10085 | B5: 45840 | C5: South | D5: Chennai | E5: Online | F5: Individual | G5: Mouse | H5: Accessories | I5: 3 | J5: 990 | K5: 0 | L5: Net Banking | M5: Vikram Singh | N5: Cancelled | O5: 0 | P5: 0 | Q5: 0 | S5: =DATE(YEAR(B5),MONTH(B5),1) -> 45839
A6: ORD-10198 | B6: 45840 | C6: South | D6: Hyderabad | E6: Retail Store | F6: Individual | G6: Printer | H6: Office Equipment | I6: 2 | J6: 13300 | K6: 0.15 | L6: Cash on Delivery | M6: Sneha Iyer | N6: Delivered | O6: 26600 | P6: 3990 | Q6: 22610 | R6: 3 | S6: =DATE(YEAR(B6),MONTH(B6),1) -> 45839
A7: ORD-10526 | B7: 45840 | C7: North | D7: Noida | E7: Retail Store | F7: Enterprise | G7: Smartphone | H7: Electronics | I7: 1 | J7: 29800 | K7: 0.1 | L7: Debit Card | M7: Karan Patel | N7: Delivered | O7: 29800 | P7: 2980 | Q7: 26820 | R7: 3 | S7: =DATE(YEAR(B7),MONTH(B7),1) -> 45839
A8: ORD-10121 | B8: 45840 | C8: North | D8: Delhi | E8: Retail Store | F8: Small Business | G8: External SSD | H8: Storage | I8: 1 | J8: 6710 | K8: 0 | L8: Net Banking | M8: Vikram Singh | N8: Delivered | O8: 6710 | P8: 0 | Q8: 6710 | R8: 2 | S8: =DATE(YEAR(B8),MONTH(B8),1) -> 45839
A9: ORD-10109 | B9: 45842 | C9: West | D9: Mumbai | E9: Online | F9: Small Business | G9: Keyboard | H9: Accessories | I9: 3 | J9: 1790 | K9: 0.05 | L9: Net Banking | M9: Sneha Iyer | N9: Delivered | O9: 5370 | P9: 268.5 | Q9: 5101.5 | R9: 3 | S9: =DATE(YEAR(B9),MONTH(B9),1) -> 45839
A10: ORD-10527 | B10: 45842 | C10: West | D10: Mumbai | E10: Online | F10: Small Business | G10: External SSD | H10: Storage | I10: 2 | J10: 6850 | K10: 0.05 | L10: UPI | M10: Rohan Sharma | N10: Delivered | O10: 13700 | P10: 685 | Q10: 13015 | R10: 3 | S10: =DATE(YEAR(B10),MONTH(B10),1) -> 45839
A11: ORD-10083 | B11: 45842 | C11: North | D11: Delhi | E11: Retail Store | F11: Enterprise | G11: External SSD | H11: Storage | I11: 4 | J11: 6700 | K11: 0.03 | L11: UPI | M11: Ananya Rao | N11: Delivered | O11: 26800 | P11: 804 | Q11: 25996 | R11: 4 | S11: =DATE(YEAR(B11),MONTH(B11),1) -> 45839
A12: ORD-10320 | B12: 45842 | C12: West | D12: Surat | E12: Online | F12: Individual | G12: Keyboard | H12: Accessories | I12: 1 | J12: 1740 | K12: 0 | L12: Credit Card | M12: Priya Nair | N12: Delivered | O12: 1740 | P12: 0 | Q12: 1740 | R12: 4 | S12: =DATE(YEAR(B12),MONTH(B12),1) -> 45839
A13: ORD-10530 | B13: 45843 | C13: West | D13: Mumbai | E13: Corporate | F13: Individual | G13: Mouse | H13: Accessories | I13: 5 | J13: 950 | K13: 0.1 | L13: UPI | M13: Neha Kapoor | N13: Delivered | O13: 4750 | P13: 475 | Q13: 4275 | R13: 3 | S13: =DATE(YEAR(B13),MONTH(B13),1) -> 45839
A14: ORD-10565 | B14: 45843 | C14: South | D14: Hyderabad | E14: Online | F14: Individual | G14: Office Chair | H14: Furniture | I14: 2 | J14: 11810 | K14: 0.08 | L14: Credit Card | M14: Neha Kapoor | N14: Delivered | O14: 23620 | P14: 1889.6 | Q14: 21730.4 | R14: 2 | S14: =DATE(YEAR(B14),MONTH(B14),1) -> 45839
A15: ORD-10375 | B15: 45844 | C15: South | D15: Chennai | E15: Retail Store | F15: Individual | G15: Laptop | H15: Electronics | I15: 3 | J15: 64490 | K15: 0 | L15: Net Banking | M15: Aarav Mehta | N15: Delivered | O15: 193470 | P15: 0 | Q15: 193470 | R15: 1 | S15: =DATE(YEAR(B15),MONTH(B15),1) -> 45839
A16: ORD-10381 | B16: 45844 | C16: West | D16: Surat | E16: Online | F16: Individual | G16: Laptop | H16: Electronics | I16: 1 | J16: 64500 | K16: 0.08 | L16: Net Banking | M16: Priya Nair | N16: Delivered | O16: 64500 | P16: 5160 | Q16: 59340 | R16: 5 | S16: =DATE(YEAR(B16),MONTH(B16),1) -> 45839
A17: ORD-10330 | B17: 45844 | C17: West | D17: Pune | E17: Retail Store | F17: Individual | G17: External SSD | H17: Storage | I17: 4 | J17: 7640 | K17: 0.05 | L17: Credit Card | M17: Priya Nair | N17: Delivered | O17: 30560 | P17: 1528 | Q17: 29032 | R17: 2 | S17: =DATE(YEAR(B17),MONTH(B17),1) -> 45839
... A43: ORD-10327 | B43: 45861 | C43: North | D43: Delhi | E43: Corporate | F43: Individual | G43: Keyboard | H43: Accessories | I43: 1 | J43: 1740 | K43: 0.08 | L43: Net Banking | M43: Sneha Iyer | N43: Delivered | O43: 1740 | P43: 139.2 | Q43: 1600.8 | R43: 3 | S43: =DATE(YEAR(B43),MONTH(B43),1) -> 45839
A44: ORD-10144 | B44: 45861 | C44: South | D44: Kochi | E44: Corporate | F44: Individual | G44: Wireless Headphones | H44: Electronics | I44: 1 | J44: 3170 | K44: 0 | L44: UPI | M44: Priya Nair | N44: Cancelled | O44: 0 | P44: 0 | Q44: 0 | S44: =DATE(YEAR(B44),MONTH(B44),1) -> 45839
A45: ORD-10385 | B45: 45861 | C45: West | D45: Pune | E45: Retail Store | F45: Individual | G45: Mouse | H45: Accessories | I45: 2 | J45: 880 | K45: 0.08 | L45: Credit Card | M45: Rohan Sharma | N45: Delivered | O45: 1760 | P45: 140.8 | Q45: 1619.2 | R45: 1 | S45: =DATE(YEAR(B45),MONTH(B45),1) -> 45839
A46: ORD-10631 | B46: 45861 | C46: South | D46: Hyderabad | E46: Corporate | F46: Enterprise | G46: Monitor | H46: Electronics | I46: 1 | J46: 17400 | K46: 0.05 | L46: UPI | M46: Karan Patel | N46: Delivered | O46: 17400 | P46: 870 | Q46: 16530 | R46: 3 | S46: =DATE(YEAR(B46),MONTH(B46),1) -> 45839
A47: ORD-10432 | B47: 45863 | C47: West | D47: Mumbai | E47: Online | F47: Individual | G47: Wireless Headphones | H47: Electronics | I47: 1 | J47: 3030 | K47: 0.03 | L47: Net Banking | M47: Aarav Mehta | N47: Delivered | O47: 3030 | P47: 90.9 | Q47: 2939.1 | R47: 5 | S47: =DATE(YEAR(B47),MONTH(B47),1) -> 45839
A48: ORD-10536 | B48: 45863 | C48: South | D48: Kochi | E48: Corporate | F48: Small Business | G48: Wireless Headphones | H48: Electronics | I48: 2 | J48: 3140 | K48: 0.1 | L48: Debit Card | M48: Karan Patel | N48: Delivered | O48: 6280 | P48: 628 | Q48: 5652 | R48: 2 | S48: =DATE(YEAR(B48),MONTH(B48),1) -> 45839
A49: ORD-10328 | B49: 45863 | C49: West | D49: Ahmedabad | E49: Corporate | F49: Individual | G49: Laptop | H49: Electronics | I49: 2 | J49: 60000 | K49: 0.03 | L49: UPI | M49: Sneha Iyer | N49: Delivered | O49: 120000 | P49: 3600 | Q49: 116400 | R49: 2 | S49: =DATE(YEAR(B49),MONTH(B49),1) -> 45839
A50: ORD-10476 | B50: 45863 | C50: East | D50: Bhubaneswar | E50: Retail Store | F50: Enterprise | G50: Laptop | H50: Electronics | I50: 1 | J50: 59470 | K50: 0.08 | L50: Debit Card | M50: Karan Patel | N50: Delivered | O50: 59470 | P50: 4757.6 | Q50: 54712.4 | R50: 1 | S50: =DATE(YEAR(B50),MONTH(B50),1) -> 45839
A51: ORD-10590 | B51: 45865 | C51: North | D51: Delhi | E51: Online | F51: Small Business | G51: Laptop | H51: Electronics | I51: 1 | J51: 65160 | K51: 0 | L51: Credit Card | M51: Ananya Rao | N51: Delivered | O51: 65160 | P51: 0 | Q51: 65160 | R51: 2 | S51: =DATE(YEAR(B51),MONTH(B51),1) -> 45839
A52: ORD-10143 | B52: 45865 | C52: South | D52: Chennai | E52: Online | F52: Small Business | G52: Printer | H52: Office Equipment | I52: 1 | J52: 13060 | K52: 0.08 | L52: UPI | M52: Vikram Singh | N52: Delivered | O52: 13060 | P52: 1044.8 | Q52: 12015.2 | R52: 4 | S52: =DATE(YEAR(B52),MONTH(B52),1) -> 45839
A53: ORD-10141 | B53: 45865 | C53: North | D53: Lucknow | E53: Online | F53: Individual | G53: Power Bank | H53: Accessories | I53: 2 | J53: 1680 | K53: 0.03 | L53: UPI | M53: Priya Nair | N53: Delivered | O53: 3360 | P53: 100.8 | Q53: 3259.2 | R53: 4 | S53: =DATE(YEAR(B53),MONTH(B53),1) -> 45839
A54: ORD-10305 | B54: 45866 | C54: South | D54: Bengaluru | E54: Retail Store | F54: Individual | G54: Laptop | H54: Electronics | I54: 3 | J54: 65510 | K54: 0.08 | L54: Credit Card | M54: Neha Kapoor | N54: Delivered | O54: 196530 | P54: 15722.4 | Q54: 180807.6 | R54: 3 | S54: =DATE(YEAR(B54),MONTH(B54),1) -> 45839
A55: ORD-10507 | B55: 45866 | C55: West | D55: Surat | E55: Online | F55: Small Business | G55: Wireless Headphones | H55: Electronics | I55: 5 | J55: 3320 | K55: 0.05 | L55: UPI | M55: Priya Nair | N55: Delivered | O55: 16600 | P55: 830 | Q55: 15770 | R55: 3 | S55: =DATE(YEAR(B55),MONTH(B55),1) -> 45839
A56: ORD-10388 | B56: 45866 | C56: North | D56: Delhi | E56: Retail Store | F56: Enterprise | G56: Wireless Headphones | H56: Electronics | I56: 1 | J56: 3310 | K56: 0.05 | L56: Debit Card | M56: Neha Kapoor | N56: Delivered | O56: 3310 | P56: 165.5 | Q56: 3144.5 | R56: 4 | S56: =DATE(YEAR(B56),MONTH(B56),1) -> 45839
... A120: ORD-10436 | B120: 45898 | C120: North | D120: Jaipur | E120: Retail Store | F120: Individual | G120: Office Chair | H120: Furniture | I120: 2 | J120: 10780 | K120: 0.08 | L120: Debit Card | M120: Neha Kapoor | N120: Delivered | O120: 21560 | P120: 1724.8 | Q120: 19835.2 | R120: 2 | S120: =DATE(YEAR(B120),MONTH(B120),1) -> 45870
A121: ORD-10072 | B121: 45901 | C121: South | D121: Kochi | E121: Retail Store | F121: Small Business | G121: Webcam | H121: Accessories | I121: 1 | J121: 3750 | K121: 0.08 | L121: UPI | M121: Rohan Sharma | N121: Cancelled | O121: 0 | P121: 0 | Q121: 0 | S121: =DATE(YEAR(B121),MONTH(B121),1) -> 45901
A122: ORD-10273 | B122: 45901 | C122: West | D122: Surat | E122: Retail Store | F122: Individual | G122: Mouse | H122: Accessories | I122: 1 | J122: 910 | K122: 0.15 | L122: Debit Card | M122: Ananya Rao | N122: Delivered | O122: 910 | P122: 136.5 | Q122: 773.5 | R122: 3 | S122: =DATE(YEAR(B122),MONTH(B122),1) -> 45901
A123: ORD-10060 | B123: 45901 | C123: West | D123: Surat | E123: Corporate | F123: Individual | G123: Smartphone | H123: Electronics | I123: 4 | J123: 27810 | K123: 0.03 | L123: Credit Card | M123: Karan Patel | N123: Delivered | O123: 111240 | P123: 3337.2 | Q123: 107902.8 | R123: 5 | S123: =DATE(YEAR(B123),MONTH(B123),1) -> 45901
A124: ORD-10369 | B124: 45903 | C124: South | D124: Bengaluru | E124: Online | F124: Individual | G124: External SSD | H124: Storage | I124: 1 | J124: 6750 | K124: 0 | L124: Net Banking | M124: Rohan Sharma | N124: Delivered | O124: 6750 | P124: 0 | Q124: 6750 | R124: 6 | S124: =DATE(YEAR(B124),MONTH(B124),1) -> 45901
A125: ORD-10452 | B125: 45903 | C125: West | D125: Mumbai | E125: Online | F125: Individual | G125: Backpack | H125: Accessories | I125: 1 | J125: 2450 | K125: 0 | L125: UPI | M125: Ananya Rao | N125: Delivered | O125: 2450 | P125: 0 | Q125: 2450 | R125: 2 | S125: =DATE(YEAR(B125),MONTH(B125),1) -> 45901
A126: ORD-10363 | B126: 45904 | C126: South | D126: Hyderabad | E126: Online | F126: Individual | G126: Monitor | H126: Electronics | I126: 5 | J126: 15940 | K126: 0.1 | L126: Net Banking | M126: Rohan Sharma | N126: Delivered | O126: 79700 | P126: 7970 | Q126: 71730 | R126: 2 | S126: =DATE(YEAR(B126),MONTH(B126),1) -> 45901
A127: ORD-10033 | B127: 45904 | C127: West | D127: Pune | E127: Online | F127: Individual | G127: External SSD | H127: Storage | I127: 5 | J127: 7250 | K127: 0.08 | L127: Credit Card | M127: Rohan Sharma | N127: Delivered | O127: 36250 | P127: 2900 | Q127: 33350 | R127: 2 | S127: =DATE(YEAR(B127),MONTH(B127),1) -> 45901
A128: ORD-10249 | B128: 45904 | C128: South | D128: Hyderabad | E128: Retail Store | F128: Small Business | G128: Tablet | H128: Electronics | I128: 2 | J128: 22660 | K128: 0.05 | L128: Credit Card | M128: Sneha Iyer | N128: Delivered | O128: 45320 | P128: 2266 | Q128: 43054 | R128: 4 | S128: =DATE(YEAR(B128),MONTH(B128),1) -> 45901
A129: ORD-10315 | B129: 45906 | C129: South | D129: Bengaluru | E129: Retail Store | F129: Small Business | G129: Smartphone | H129: Electronics | I129: 4 | J129: 26590 | K129: 0.08 | L129: Debit Card | M129: Aarav Mehta | N129: Delivered | O129: 106360 | P129: 8508.8 | Q129: 97851.2 | R129: 7 | S129: =DATE(YEAR(B129),MONTH(B129),1) -> 45901
A130: ORD-10300 | B130: 45907 | C130: South | D130: Hyderabad | E130: Online | F130: Small Business | G130: Mouse | H130: Accessories | I130: 2 | J130: 910 | K130: 0 | L130: Credit Card | M130: Neha Kapoor | N130: Delivered | O130: 1820 | P130: 0 | Q130: 1820 | R130: 3 | S130: =DATE(YEAR(B130),MONTH(B130),1) -> 45901
A131: ORD-10608 | B131: 45907 | C131: South | D131: Kochi | E131: Retail Store | F131: Individual | G131: Mouse | H131: Accessories | I131: 3 | J131: 910 | K131: 0.05 | L131: Credit Card | M131: Ananya Rao | N131: Delivered | O131: 2730 | P131: 136.5 | Q131: 2593.5 | R131: 3 | S131: =DATE(YEAR(B131),MONTH(B131),1) -> 45901
A132: ORD-10277 | B132: 45907 | C132: South | D132: Hyderabad | E132: Online | F132: Individual | G132: Tablet | H132: Electronics | I132: 1 | J132: 22380 | K132: 0 | L132: Credit Card | M132: Sneha Iyer | N132: Delivered | O132: 22380 | P132: 0 | Q132: 22380 | R132: 3 | S132: =DATE(YEAR(B132),MONTH(B132),1) -> 45901
A133: ORD-10573 | B133: 45908 | C133: North | D133: Lucknow | E133: Online | F133: Enterprise | G133: Backpack | H133: Accessories | I133: 1 | J133: 2480 | K133: 0 | L133: Credit Card | M133: Sneha Iyer | N133: Delivered | O133: 2480 | P133: 0 | Q133: 2480 | R133: 2 | S133: =DATE(YEAR(B133),MONTH(B133),1) -> 45901
... A155: ORD-10177 | B155: 45919 | C155: North | D155: Lucknow | E155: Online | F155: Individual | G155: External SSD | H155: Storage | I155: 4 | J155: 7220 | K155: 0 | L155: Net Banking | M155: Rohan Sharma | N155: Delivered | O155: 28880 | P155: 0 | Q155: 28880 | R155: 3 | S155: =DATE(YEAR(B155),MONTH(B155),1) -> 45901
A156: ORD-10224 | B156: 45919 | C156: North | D156: Noida | E156: Retail Store | F156: Small Business | G156: Mouse | H156: Accessories | I156: 1 | J156: 940 | K156: 0.03 | L156: UPI | M156: Rohan Sharma | N156: Cancelled | O156: 0 | P156: 0 | Q156: 0 | S156: =DATE(YEAR(B156),MONTH(B156),1) -> 45901
A157: ORD-10152 | B157: 45921 | C157: South | D157: Chennai | E157: Online | F157: Individual | G157: Office Chair | H157: Furniture | I157: 2 | J157: 11640 | K157: 0.08 | L157: UPI | M157: Ananya Rao | N157: Delivered | O157: 23280 | P157: 1862.4 | Q157: 21417.6 | R157: 5 | S157: =DATE(YEAR(B157),MONTH(B157),1) -> 45901
A158: ORD-10131 | B158: 45922 | C158: South | D158: Hyderabad | E158: Retail Store | F158: Enterprise | G158: Office Chair | H158: Furniture | I158: 1 | J158: 10900 | K158: 0 | L158: UPI | M158: Vikram Singh | N158: Delivered | O158: 10900 | P158: 0 | Q158: 10900 | R158: 2 | S158: =DATE(YEAR(B158),MONTH(B158),1) -> 45901
A159: ORD-10419 | B159: 45923 | C159: East | D159: Bhubaneswar | E159: Online | F159: Individual | G159: Keyboard | H159: Accessories | I159: 3 | J159: 1750 | K159: 0 | L159: Cash on Delivery | M159: Ananya Rao | N159: Returned | O159: 5250 | P159: 0 | Q159: 5250 | R159: 3 | S159: =DATE(YEAR(B159),MONTH(B159),1) -> 45901
A160: ORD-10057 | B160: 45923 | C160: East | D160: Guwahati | E160: Online | F160: Small Business | G160: Office Desk | H160: Furniture | I160: 2 | J160: 15160 | K160: 0.05 | L160: UPI | M160: Ananya Rao | N160: Delivered | O160: 30320 | P160: 1516 | Q160: 28804 | R160: 4 | S160: =DATE(YEAR(B160),MONTH(B160),1) -> 45901
A161: ORD-10031 | B161: 45924 | C161: North | D161: Lucknow | E161: Corporate | F161: Individual | G161: Laptop | H161: Electronics | I161: 1 | J161: 57830 | K161: 0.08 | L161: UPI | M161: Ananya Rao | N161: Delivered | O161: 57830 | P161: 4626.4 | Q161: 53203.6 | R161: 3 | S161: =DATE(YEAR(B161),MONTH(B161),1) -> 45901
A162: ORD-10256 | B162: 45926 | C162: South | D162: Bengaluru | E162: Online | F162: Small Business | G162: External SSD | H162: Storage | I162: 2 | J162: 6830 | K162: 0.05 | L162: UPI | M162: Neha Kapoor | N162: Delivered | O162: 13660 | P162: 683 | Q162: 12977 | R162: 2 | S162: =DATE(YEAR(B162),MONTH(B162),1) -> 45901
A163: ORD-10080 | B163: 45927 | C163: North | D163: Jaipur | E163: Retail Store | F163: Enterprise | G163: Tablet | H163: Electronics | I163: 3 | J163: 21800 | K163: 0.05 | L163: UPI | M163: Priya Nair | N163: Delivered | O163: 65400 | P163: 3270 | Q163: 62130 | R163: 2 | S163: =DATE(YEAR(B163),MONTH(B163),1) -> 45901
A164: ORD-10310 | B164: 45927 | C164: South | D164: Hyderabad | E164: Retail Store | F164: Individual | G164: Mouse | H164: Accessories | I164: 1 | J164: 990 | K164: 0.03 | L164: UPI | M164: Vikram Singh | N164: Delivered | O164: 990 | P164: 29.7 | Q164: 960.3 | R164: 2 | S164: =DATE(YEAR(B164),MONTH(B164),1) -> 45901
A165: ORD-10368 | B165: 45927 | C165: West | D165: Ahmedabad | E165: Corporate | F165: Individual | G165: Wireless Headphones | H165: Electronics | I165: 1 | J165: 3280 | K165: 0.08 | L165: Net Banking | M165: Karan Patel | N165: Cancelled | O165: 0 | P165: 0 | Q165: 0 | S165: =DATE(YEAR(B165),MONTH(B165),1) -> 45901
A166: ORD-10458 | B166: 45927 | C166: West | D166: Pune | E166: Retail Store | F166: Individual | G166: Webcam | H166: Accessories | I166: 3 | J166: 3580 | K166: 0.08 | L166: Credit Card | M166: Aarav Mehta | N166: Delivered | O166: 10740 | P166: 859.2 | Q166: 9880.8 | R166: 4 | S166: =DATE(YEAR(B166),MONTH(B166),1) -> 45901
A167: ORD-10535 | B167: 45928 | C167: West | D167: Mumbai | E167: Online | F167: Individual | G167: Smartphone | H167: Electronics | I167: 3 | J167: 29910 | K167: 0.05 | L167: UPI | M167: Aarav Mehta | N167: Delivered | O167: 89730 | P167: 4486.5 | Q167: 85243.5 | R167: 4 | S167: =DATE(YEAR(B167),MONTH(B167),1) -> 45901
A168: ORD-10262 | B168: 45928 | C168: East | D168: Guwahati | E168: Online | F168: Small Business | G168: External SSD | H168: Storage | I168: 1 | J168: 7040 | K168: 0.03 | L168: Credit Card | M168: Karan Patel | N168: Delivered | O168: 7040 | P168: 211.2 | Q168: 6828.8 | R168: 2 | S168: =DATE(YEAR(B168),MONTH(B168),1) -> 45901
A169: ORD-10183 | B169: 45928 | C169: South | D169: Hyderabad | E169: Retail Store | F169: Individual | G169: Office Chair | H169: Furniture | I169: 1 | J169: 11810 | K169: 0 | L169: Credit Card | M169: Karan Patel | N169: Delivered | O169: 11810 | P169: 0 | Q169: 11810 | R169: 7 | S169: =DATE(YEAR(B169),MONTH(B169),1) -> 45901
A170: ORD-10022 | B170: 45928 | C170: South | D170: Kochi | E170: Retail Store | F170: Individual | G170: Mouse | H170: Accessories | I170: 2 | J170: 1000 | K170: 0 | L170: Debit Card | M170: Ananya Rao | N170: Delivered | O170: 2000 | P170: 0 | Q170: 2000 | R170: 5 | S170: =DATE(YEAR(B170),MONTH(B170),1) -> 45901
A171: ORD-10619 | B171: 45929 | C171: South | D171: Kochi | E171: Online | F171: Enterprise | G171: Smartphone | H171: Electronics | I171: 2 | J171: 27300 | K171: 0.08 | L171: Net Banking | M171: Vikram Singh | N171: Delivered | O171: 54600 | P171: 4368 | Q171: 50232 | R171: 3 | S171: =DATE(YEAR(B171),MONTH(B171),1) -> 45901
A172: ORD-10230 | B172: 45930 | C172: West | D172: Pune | E172: Corporate | F172: Individual | G172: Smartphone | H172: Electronics | I172: 1 | J172: 27340 | K172: 0.05 | L172: Debit Card | M172: Karan Patel | N172: Delivered | O172: 27340 | P172: 1367 | Q172: 25973 | R172: 2 | S172: =DATE(YEAR(B172),MONTH(B172),1) -> 45901
A173: ORD-10104 | B173: 45930 | C173: West | D173: Pune | E173: Retail Store | F173: Individual | G173: Webcam | H173: Accessories | I173: 1 | J173: 3400 | K173: 0.05 | L173: Debit Card | M173: Karan Patel | N173: Delivered | O173: 3400 | P173: 170 | Q173: 3230 | R173: 3 | S173: =DATE(YEAR(B173),MONTH(B173),1) -> 45901
A174: ORD-10160 | B174: 45931 | C174: South | D174: Hyderabad | E174: Retail Store | F174: Enterprise | G174: Backpack | H174: Accessories | I174: 3 | J174: 2510 | K174: 0.05 | L174: Net Banking | M174: Aarav Mehta | N174: Cancelled | O174: 0 | P174: 0 | Q174: 0 | S174: =DATE(YEAR(B174),MONTH(B174),1) -> 45931
A175: ORD-10189 | B175: 45932 | C175: East | D175: Kolkata | E175: Corporate | F175: Small Business | G175: External SSD | H175: Storage | I175: 4 | J175: 6720 | K175: 0.15 | L175: Credit Card | M175: Rohan Sharma | N175: Delivered | O175: 26880 | P175: 4032 | Q175: 22848 | R175: 3 | S175: =DATE(YEAR(B175),MONTH(B175),1) -> 45931
A176: ORD-10297 | B176: 45933 | C176: South | D176: Chennai | E176: Corporate | F176: Small Business | G176: Webcam | H176: Accessories | I176: 1 | J176: 3410 | K176: 0.05 | L176: UPI | M176: Aarav Mehta | N176: Delivered | O176: 3410 | P176: 170.5 | Q176: 3239.5 | R176: 5 | S176: =DATE(YEAR(B176),MONTH(B176),1) -> 45931
A177: ORD-10361 | B177: 45934 | C177: South | D177: Bengaluru | E177: Retail Store | F177: Small Business | G177: Power Bank | H177: Accessories | I177: 3 | J177: 1700 | K177: 0 | L177: Net Banking | M177: Neha Kapoor | N177: Delivered | O177: 5100 | P177: 0 | Q177: 5100 | R177: 2 | S177: =DATE(YEAR(B177),MONTH(B177),1) -> 45931
A178: ORD-10246 | B178: 45935 | C178: South | D178: Chennai | E178: Retail Store | F178: Individual | G178: Laptop | H178: Electronics | I178: 2 | J178: 66280 | K178: 0.03 | L178: Net Banking | M178: Sneha Iyer | N178: Delivered | O178: 132560 | P178: 3976.8 | Q178: 128583.2 | R178: 4 | S178: =DATE(YEAR(B178),MONTH(B178),1) -> 45931
A179: ORD-10382 | B179: 45935 | C179: East | D179: Kolkata | E179: Retail Store | F179: Individual | G179: Tablet | H179: Electronics | I179: 1 | J179: 23320 | K179: 0.05 | L179: Cash on Delivery | M179: Rohan Sharma | N179: Delivered | O179: 23320 | P179: 1166 | Q179: 22154 | R179: 5 | S179: =DATE(YEAR(B179),MONTH(B179),1) -> 45931
A180: ORD-10235 | B180: 45936 | C180: West | D180: Surat | E180: Retail Store | F180: Individual | G180: Laptop | H180: Electronics | I180: 1 | J180: 57700 | K180: 0.03 | L180: Cash on Delivery | M180: Neha Kapoor | N180: Delivered | O180: 57700 | P180: 1731 | Q180: 55969 | R180: 4 | S180: =DATE(YEAR(B180),MONTH(B180),1) -> 45931
A181: ORD-10065 | B181: 45937 | C181: East | D181: Guwahati | E181: Online | F181: Small Business | G181: Mouse | H181: Accessories | I181: 1 | J181: 1010 | K181: 0.08 | L181: Debit Card | M181: Rohan Sharma | N181: Delivered | O181: 1010 | P181: 80.8 | Q181: 929.2 | R181: 4 | S181: =DATE(YEAR(B181),MONTH(B181),1) -> 45931
A182: ORD-10600 | B182: 45937 | C182: East | D182: Bhubaneswar | E182: Online | F182: Individual | G182: Office Desk | H182: Furniture | I182: 2 | J182: 14130 | K182: 0.15 | L182: Net Banking | M182: Priya Nair | N182: Delivered | O182: 28260 | P182: 4239 | Q182: 24021 | R182: 2 | S182: =DATE(YEAR(B182),MONTH(B182),1) -> 45931
A183: ORD-10366 | B183: 45938 | C183: South | D183: Kochi | E183: Retail Store | F183: Small Business | G183: External SSD | H183: Storage | I183: 1 | J183: 6950 | K183: 0.03 | L183: Net Banking | M183: Vikram Singh | N183: Cancelled | O183: 0 | P183: 0 | Q183: 0 | S183: =DATE(YEAR(B183),MONTH(B183),1) -> 45931
A184: ORD-10383 | B184: 45938 | C184: North | D184: Noida | E184: Retail Store | F184: Individual | G184: Office Desk | H184: Furniture | I184: 2 | J184: 13910 | K184: 0.08 | L184: Debit Card | M184: Rohan Sharma | N184: Delivered | O184: 27820 | P184: 2225.6 | Q184: 25594.4 | R184: 4 | S184: =DATE(YEAR(B184),MONTH(B184),1) -> 45931
A185: ORD-10461 | B185: 45940 | C185: West | D185: Pune | E185: Online | F185: Enterprise | G185: Smartphone | H185: Electronics | I185: 2 | J185: 26710 | K185: 0.05 | L185: Net Banking | M185: Ananya Rao | N185: Delivered | O185: 53420 | P185: 2671 | Q185: 50749 | R185: 3 | S185: =DATE(YEAR(B185),MONTH(B185),1) -> 45931
A186: ORD-10103 | B186: 45940 | C186: East | D186: Kolkata | E186: Online | F186: Individual | G186: Tablet | H186: Electronics | I186: 2 | J186: 20980 | K186: 0.05 | L186: UPI | M186: Ananya Rao | N186: Delivered | O186: 41960 | P186: 2098 | Q186: 39862 | R186: 3 | S186: =DATE(YEAR(B186),MONTH(B186),1) -> 45931
A187: ORD-10613 | B187: 45941 | C187: South | D187: Hyderabad | E187: Retail Store | F187: Enterprise | G187: External SSD | H187: Storage | I187: 1 | J187: 7650 | K187: 0 | L187: Credit Card | M187: Rohan Sharma | N187: Delivered | O187: 7650 | P187: 0 | Q187: 7650 | R187: 3 | S187: =DATE(YEAR(B187),MONTH(B187),1) -> 45931
A188: ORD-10111 | B188: 45942 | C188: East | D188: Guwahati | E188: Online | F188: Individual | G188: Smartphone | H188: Electronics | I188: 1 | J188: 28240 | K188: 0.1 | L188: UPI | M188: Neha Kapoor | N188: Delivered | O188: 28240 | P188: 2824 | Q188: 25416 | R188: 5 | S188: =DATE(YEAR(B188),MONTH(B188),1) -> 45931
A189: ORD-10564 | B189: 45942 | C189: North | D189: Jaipur | E189: Retail Store | F189: Individual | G189: Keyboard | H189: Accessories | I189: 2 | J189: 1850 | K189: 0.05 | L189: Cash on Delivery | M189: Vikram Singh | N189: Delivered | O189: 3700 | P189: 185 | Q189: 3515 | R189: 4 | S189: =DATE(YEAR(B189),MONTH(B189),1) -> 45931
A190: ORD-10309 | B190: 45943 | C190: North | D190: Delhi | E190: Online | F190: Individual | G190: Wireless Headphones | H190: Electronics | I190: 1 | J190: 3010 | K190: 0 | L190: Debit Card | M190: Sneha Iyer | N190: Delivered | O190: 3010 | P190: 0 | Q190: 3010 | R190: 2 | S190: =DATE(YEAR(B190),MONTH(B190),1) -> 45931
A191: ORD-10625 | B191: 45943 | C191: West | D191: Surat | E191: Online | F191: Individual | G191: External SSD | H191: Storage | I191: 1 | J191: 7000 | K191: 0 | L191: Cash on Delivery | M191: Priya Nair | N191: Delivered | O191: 7000 | P191: 0 | Q191: 7000 | R191: 2 | S191: =DATE(YEAR(B191),MONTH(B191),1) -> 45931
A192: ORD-10231 | B192: 45944 | C192: North | D192: Lucknow | E192: Online | F192: Individual | G192: Wireless Headphones | H192: Electronics | I192: 2 | J192: 3200 | K192: 0.03 | L192: Credit Card | M192: Karan Patel | N192: Delivered | O192: 6400 | P192: 192 | Q192: 6208 | R192: 3 | S192: =DATE(YEAR(B192),MONTH(B192),1) -> 45931
A193: ORD-10237 | B193: 45944 | C193: South | D193: Chennai | E193: Corporate | F193: Individual | G193: External SSD | H193: Storage | I193: 2 | J193: 6740 | K193: 0.1 | L193: Credit Card | M193: Aarav Mehta | N193: Delivered | O193: 13480 | P193: 1348 | Q193: 12132 | R193: 7 | S193: =DATE(YEAR(B193),MONTH(B193),1) -> 45931
A194: ORD-10412 | B194: 45944 | C194: West | D194: Pune | E194: Retail Store | F194: Small Business | G194: Office Desk | H194: Furniture | I194: 1 | J194: 13960 | K194: 0.03 | L194: UPI | M194: Ananya Rao | N194: Delivered | O194: 13960 | P194: 418.8 | Q194: 13541.2 | R194: 3 | S194: =DATE(YEAR(B194),MONTH(B194),1) -> 45931
A195: ORD-10081 | B195: 45945 | C195: South | D195: Kochi | E195: Online | F195: Individual | G195: Office Chair | H195: Furniture | I195: 1 | J195: 11340 | K195: 0 | L195: UPI | M195: Priya Nair | N195: Delivered | O195: 11340 | P195: 0 | Q195: 11340 | R195: 4 | S195: =DATE(YEAR(B195),MONTH(B195),1) -> 45931
... A273: ORD-10025 | B273: 45990 | C273: South | D273: Hyderabad | E273: Online | F273: Individual | G273: Smartphone | H273: Electronics | I273: 1 | J273: 29720 | K273: 0 | L273: UPI | M273: Neha Kapoor | N273: Delivered | O273: 29720 | P273: 0 | Q273: 29720 | R273: 1 | S273: =DATE(YEAR(B273),MONTH(B273),1) -> 45962
A274: ORD-10258 | B274: 45990 | C274: North | D274: Delhi | E274: Retail Store | F274: Small Business | G274: Office Desk | H274: Furniture | I274: 1 | J274: 13510 | K274: 0.05 | L274: Credit Card | M274: Rohan Sharma | N274: Cancelled | O274: 0 | P274: 0 | Q274: 0 | S274: =DATE(YEAR(B274),MONTH(B274),1) -> 45962
A275: ORD-10280 | B275: 45990 | C275: East | D275: Guwahati | E275: Retail Store | F275: Individual | G275: Backpack | H275: Accessories | I275: 2 | J275: 2340 | K275: 0.1 | L275: Cash on Delivery | M275: Karan Patel | N275: Delivered | O275: 4680 | P275: 468 | Q275: 4212 | R275: 1 | S275: =DATE(YEAR(B275),MONTH(B275),1) -> 45962
A276: ORD-10153 | B276: 45991 | C276: East | D276: Kolkata | E276: Retail Store | F276: Individual | G276: Tablet | H276: Electronics | I276: 1 | J276: 23240 | K276: 0 | L276: UPI | M276: Priya Nair | N276: Returned | O276: 23240 | P276: 0 | Q276: 23240 | R276: 5 | S276: =DATE(YEAR(B276),MONTH(B276),1) -> 45962
A277: ORD-10621 | B277: 45992 | C277: East | D277: Kolkata | E277: Corporate | F277: Small Business | G277: Printer | H277: Office Equipment | I277: 3 | J277: 12710 | K277: 0.03 | L277: Net Banking | M277: Vikram Singh | N277: Delivered | O277: 38130 | P277: 1143.9 | Q277: 36986.1 | R277: 5 | S277: =DATE(YEAR(B277),MONTH(B277),1) -> 45992
A278: ORD-10132 | B278: 45992 | C278: West | D278: Surat | E278: Online | F278: Individual | G278: Mouse | H278: Accessories | I278: 3 | J278: 970 | K278: 0.03 | L278: UPI | M278: Ananya Rao | N278: Delivered | O278: 2910 | P278: 87.3 | Q278: 2822.7 | R278: 3 | S278: =DATE(YEAR(B278),MONTH(B278),1) -> 45992
A279: ORD-10518 | B279: 45992 | C279: South | D279: Bengaluru | E279: Retail Store | F279: Individual | G279: Office Desk | H279: Furniture | I279: 3 | J279: 13900 | K279: 0.1 | L279: Cash on Delivery | M279: Ananya Rao | N279: Delivered | O279: 41700 | P279: 4170 | Q279: 37530 | R279: 3 | S279: =DATE(YEAR(B279),MONTH(B279),1) -> 45992
A280: ORD-10220 | B280: 45992 | C280: South | D280: Bengaluru | E280: Online | F280: Individual | G280: Monitor | H280: Electronics | I280: 2 | J280: 16780 | K280: 0.1 | L280: UPI | M280: Ananya Rao | N280: Delivered | O280: 33560 | P280: 3356 | Q280: 30204 | R280: 3 | S280: =DATE(YEAR(B280),MONTH(B280),1) -> 45992
A281: ORD-10287 | B281: 45992 | C281: South | D281: Hyderabad | E281: Retail Store | F281: Individual | G281: Smartphone | H281: Electronics | I281: 1 | J281: 27170 | K281: 0.08 | L281: Credit Card | M281: Karan Patel | N281: Cancelled | O281: 0 | P281: 0 | Q281: 0 | S281: =DATE(YEAR(B281),MONTH(B281),1) -> 45992
A282: ORD-10454 | B282: 45995 | C282: North | D282: Lucknow | E282: Online | F282: Individual | G282: Keyboard | H282: Accessories | I282: 3 | J282: 1770 | K282: 0.08 | L282: Credit Card | M282: Vikram Singh | N282: Delivered | O282: 5310 | P282: 424.8 | Q282: 4885.2 | R282: 4 | S282: =DATE(YEAR(B282),MONTH(B282),1) -> 45992
A283: ORD-10583 | B283: 45995 | C283: North | D283: Noida | E283: Corporate | F283: Enterprise | G283: Monitor | H283: Electronics | I283: 1 | J283: 16400 | K283: 0 | L283: Net Banking | M283: Sneha Iyer | N283: Delivered | O283: 16400 | P283: 0 | Q283: 16400 | R283: 2 | S283: =DATE(YEAR(B283),MONTH(B283),1) -> 45992
A284: ORD-10488 | B284: 45995 | C284: West | D284: Mumbai | E284: Online | F284: Small Business | G284: Office Desk | H284: Furniture | I284: 2 | J284: 14960 | K284: 0.05 | L284: Credit Card | M284: Sneha Iyer | N284: Delivered | O284: 29920 | P284: 1496 | Q284: 28424 | R284: 3 | S284: =DATE(YEAR(B284),MONTH(B284),1) -> 45992
A285: ORD-10554 | B285: 45995 | C285: East | D285: Bhubaneswar | E285: Online | F285: Individual | G285: Tablet | H285: Electronics | I285: 3 | J285: 23350 | K285: 0.08 | L285: Cash on Delivery | M285: Priya Nair | N285: Delivered | O285: 70050 | P285: 5604 | Q285: 64446 | R285: 4 | S285: =DATE(YEAR(B285),MONTH(B285),1) -> 45992
A286: ORD-10100 | B286: 45996 | C286: South | D286: Bengaluru | E286: Corporate | F286: Small Business | G286: Smartphone | H286: Electronics | I286: 3 | J286: 26730 | K286: 0 | L286: Net Banking | M286: Sneha Iyer | N286: Delivered | O286: 80190 | P286: 0 | Q286: 80190 | R286: 6 | S286: =DATE(YEAR(B286),MONTH(B286),1) -> 45992
...

Sheet Analysis
A1: Total Net Sales | B1: =SUM(Table2[Net Sales INR]) -> 20805536
A3: Category | B3: Electronics | D3: Region | E3: Category | F3: Sum of Net Sales INR | H3: Total orders | I3: =COUNTA(Table2[Order ID]) -> 650
A4: Net Sales By Region | D4: East | E4: Accessories | F4: 120644.7 | H4: Average order value | I4: =B1/I3 -> 32008.516
A5: Region | B5: Sum of Net Sales INR | E5: Electronics | F5: 1587261.8
A6: East | B6: 1587261.8 | E6: Furniture | F6: 269369.6 | H6: Sales Channel | I6: Sum of Net Sales INR
A7: North | B7: 3140337.1 | E7: Office Equipment | F7: 117757.8 | H7: Corporate | I7: 3396095.8
A8: South | B8: 6643505.4 | E8: Storage | F8: 160603.3 | H8: Online | I8: 9729336.7
A9: West | B9: 4820276.5 | D9: East Total | F9: 2255637.2 | H9: Retail Store | I9: 7680103
A10: Grand Total | B10: 16191381 | D10: North | E10: Accessories | F10: 157598.8 | H10: Grand Total | I10: 20805536
E11: Electronics | F11: 3140337.1
A12: Net sales by product | E12: Furniture | F12: 533239.6
A13: Category | B13: Sum of Net Sales INR | E13: Office Equipment | F13: 70908.6
A14: Accessories | B14: 777184.8 | E14: Storage | F14: 193450.6
A15: Electronics | B15: 16191381 | D15: North Total | F15: 4095534.7
A16: Furniture | B16: 2412867.4 | D16: South | E16: Accessories | F16: 262422.4
A17: Office Equipment | B17: 610226 | E17: Electronics | F17: 6643505.4
A18: Storage | B18: 813876.5 | E18: Furniture | F18: 1025116.2
A19: Grand Total | B19: 20805536 | E19: Office Equipment | F19: 246737.6
E20: Storage | F20: 277185.9
A21: Order Status | D21: South Total | F21: 8454967.5
A22: Order Status | B22: Count of Order ID | D22: West | E22: Accessories | F22: 236518.9
A23: Cancelled | B23: 21 | E23: Electronics | F23: 4820276.5
A24: Delivered | B24: 616 | E24: Furniture | F24: 585142
A25: Returned | B25: 13 | E25: Office Equipment | F25: 174822
A26: Grand Total | B26: 650 | E26: Storage | F26: 182636.7
D27: West Total | F27: 5999396.1
A28: Cancellation rate | B28: =B23/B26 -> 0.032307692 | D28: Grand Total | F28: 20805535
A29: Return rate | B29: =B25/B26 -> 0.02
A32: Sales Month | B32: Sum of Net Sales INR
A33: 45839 | B33: 2445250.7
A34: 45870 | B34: 1299864.5
A35: 45901 | B35: 1267369.1
A36: 45931 | B36: 1603880.7
A37: 45962 | B37: 1501010.1
A38: 45992 | B38: 1699782.5
A39: 46023 | B39: 1958918.2
A40: 46054 | B40: 1120508.9
A41: 46082 | B41: 2872539.2
A42: 46113 | B42: 1374952.3
A43: 46143 | B43: 2113859.5
A44: 46174 | B44: 1547599.8
A45: Grand Total | B45: 20805536

Sheet Dashboard
A1: KEY PERFORMANCE AREAS
A3: TOTAL NET SALES | B3: TOTAL ORDERS | C3: AVERAGE ORDER VALUE | D3: CANCELLATION RATE | E3: RETURN RATE
A4: =Analysis!B1 -> 20805536 | B4: =Analysis!B26 -> 650 | C4: =Analysis!I4 -> 32008.516 | D4: =Analysis!B28 -> 0.032307692 | E4: =Analysis!B29 -> 0.02
A6: KEY INSIGHTS
A7: 1. Electronics dominates sales
A8: Electronics generated approximately 77.8% of total net sales, making it by far the largest revenue-driving category.
A9: 2. South is the strongest region
A10: South generated approximately 40.6% of total net sales, the highest among the four regions.
A11: 3. Online is the leading sales channel
A12: Online generated approximately 46.8% of total net sales, ahead of Retail Store and Corporate.
A13: 4. March 2026 was the strongest month
A14: March 2026 generated approximately ₹2.87M, the highest monthly net sales in the dataset.

Sheet Documentation
A1: Retail Sales Performance Analysis Project
A2: Excel | Data Cleaning | PivotTables | Data Visualization
A4: PROJECT OBJECTIVE
A5: Analyze retail sales data to understand revenue performance, customer orders, product categories, sales channels, regional performance, and order outcomes using Excel.
A7: BUSINESS QUESTIONS
A8: How much net sales did the business generate?
A9: Which regions generate the most revenue?
A10: Which product categories drive sales?
A11: Which sales channel performs best?
A12: How has sales performance changed over time?
A13: What proportion of orders are cancelled or returned?
A15: DATASET
... A75: Business insights
